{
  "isPromise": true,
  "volume": "Seeker.callSlowFind",
  "args": [
    {
      "pattern": "internal confidence and unification of mind",
      "showMatchesOnly": true,
      "languages": [
        "pli",
        "en"
      ],
      "maxResults": 1000,
      "searchLang": "en",
      "maxDoc": 50,
      "minLang": 2,
      "matchHighlight": "\u001b[38;5;121m$&\u001b[0m",
      "lang": "en",
      "types": [
        "root",
        "translation"
      ],
      "includeUnpublished": false
    }
  ],
  "value": {
    "lang": "en",
    "searchLang": "en",
    "minLang": 2,
    "maxDoc": 50,
    "maxResults": 1000,
    "pattern": "internal confidence and unification of mind",
    "method": "phrase",
    "resultPattern": "\\binternal confidence and unification of mind",
    "segsMatched": 0,
    "bilaraPaths": [],
    "suttaRefs": [],
    "mlDocs": []
  }
}